setup.py
src/timecalc.py
src/timecalc.egg-info/PKG-INFO
src/timecalc.egg-info/SOURCES.txt
src/timecalc.egg-info/dependency_links.txt
src/timecalc.egg-info/entry_points.txt
src/timecalc.egg-info/requires.txt
src/timecalc.egg-info/top_level.txt