Metadata-Version: 1.0
Name: timecalc
Version: 0.1.5
Summary: a tool to make the imitation of Lyubishchev and his time billing method easier
Home-page: https://github.com/yuex/timecalc
Author: Xin YUE
Author-email: yuecn41@gmail.com
License: UNKNOWN
Platform: UNKNOWN
